dedal/__init__.py
dedal/compat.py
dedal/conf.py
dedal/decorators.py
dedal/exceptions.py
dedal/models.py
dedal/site.py
dedal/views.py
dedal/static/css/bootstrap.min.css
dedal/static/fonts/glyphicons-halflings-regular.eot
dedal/static/fonts/glyphicons-halflings-regular.svg
dedal/static/fonts/glyphicons-halflings-regular.ttf
dedal/static/fonts/glyphicons-halflings-regular.woff
dedal/static/fonts/glyphicons-halflings-regular.woff2
dedal/templates/base.html
dedal/templates/dedal/_pagination.html
dedal/templates/dedal/base.html
dedal/templates/dedal/generic_create.html
dedal/templates/dedal/generic_delete.html
dedal/templates/dedal/generic_form.html
dedal/templates/dedal/generic_list.html
dedal/templates/dedal/generic_model_list.html
dedal/templates/dedal/generic_read.html
dedal/templates/dedal/generic_update.html
dedal/templatetags/__init__.py
dedal/templatetags/dedal_tags.py
django_dedal-1.1.0.dist-info/AUTHORS.rst
django_dedal-1.1.0.dist-info/LICENSE
django_dedal-1.1.0.dist-info/METADATA
django_dedal-1.1.0.dist-info/WHEEL
django_dedal-1.1.0.dist-info/top_level.txt
django_dedal-1.1.0.dist-info/RECORD
