Metadata-Version: 2.1
Name: django-dedal
Version: 1.1.0
Summary: Fast CRUD builder.
Home-page: https://github.com/ar4s/django-dedal
Author: Arkadiusz Adamski
Author-email: arkadiusz.adamski@gmail.com
License: BSD
Keywords: django-dedal
Platform: UNKNOWN
Classifier: Development Status :: 5 - Production/Stable
Classifier: Framework :: Django
Classifier: Framework :: Django :: 1.6
Classifier: Framework :: Django :: 1.7
Classifier: Framework :: Django :: 1.8
Classifier: Framework :: Django :: 1.9
Classifier: Intended Audience :: Developers
Classifier: License :: OSI Approved :: BSD License
Classifier: Natural Language :: English
Classifier: Programming Language :: Python :: 3
Classifier: Programming Language :: Python :: 3.4
Classifier: Programming Language :: Python :: 3.5
Requires-Dist: django (<2.2,>=1.8)
Requires-Dist: wheel
